playground_pypi_package_i/__init__.py
playground_pypi_package_i-0.1.5.dist-info/METADATA
playground_pypi_package_i-0.1.5.dist-info/WHEEL
playground_pypi_package_i-0.1.5.dist-info/top_level.txt
playground_pypi_package_i-0.1.5.dist-info/RECORD
